{
	"name": "ABI_LSV_MONTHLY_FEED_APP_PROD",
	"properties": {
		"linkedServiceName": {
			"referenceName": "Sftp1_connections_ALL_FEED",
			"type": "LinkedServiceReference"
		},
		"annotations": [],
		"type": "DelimitedText",
		"typeProperties": {
			"location": {
				"type": "SftpLocation",
				"fileName": "ABI_LSV_MONTHLY_FEED_PRD.txt",
				"folderPath": "/MSL_Cloud_App_Prd/FromAgency/ABI"
			},
			"columnDelimiter": "\t",
			"escapeChar": "\\",
			"firstRowAsHeader": true,
			"quoteChar": "\""
		},
		"schema": [
			{
				"name": "PERIOD_NAME\tPOLICY_NUMBER\tCLIENT_ID\tCLIENT_NAME\tCATEGORY\tPRODUCT\tWRITING_AGENT_ID\tWRITING_AGENT_NAME\tAGENT_CONTRACT_NUMBER\tPOLICY_EFFECTIVE_DATE\tPOLICY_PAID_TO_DATE\tPREMIUM_TRANSACTION_DATE\tPREMIUM_DUE_DATE\tMTHS_PAID\tPREMIUM\tRATE_PERCENTAGE\tEARNED\tADJUSTMENTS\tPAYABLE\tUNEARNED_BALANCE\tCOMMENTS\tISSUE_STATE\tINSURED_NAME\tGENDER\tADDRESS_LINE_ONE\tADDRESS_LINE_TWO\tADDRESS_LINE_THREE\tCITY\tSTATE\tZIP",
				"type": "String"
			}
		]
	},
	"type": "Microsoft.DataFactory/factories/datasets"
}